SimpleRegPythonN/__init__.py
SimpleRegPythonN/correlation.py
SimpleRegPythonN/regression.py
SimpleRegPython-0.1.dist-info/LICENCE
SimpleRegPython-0.1.dist-info/METADATA
SimpleRegPython-0.1.dist-info/WHEEL
SimpleRegPython-0.1.dist-info/top_level.txt
SimpleRegPython-0.1.dist-info/RECORD
