Metadata-Version: 2.1
Name: SimpleRegPython
Version: 0.1
Summary: A package for Pearson correlation and simple linear regression
Home-page: https://github.com/ArashArd/SimpleRegPython
Author: Arash Ardalan
Author-email: a.ardalan07@gmail.com
Classifier: Programming Language :: Python :: 3
Classifier: License :: OSI Approved :: MIT License
Classifier: Operating System :: OS Independent
Requires-Python: >=3.6
License-File: LICENCE
Requires-Dist: numpy
